Workbook

Sheet Control
A1: VietGreen V4 formula-driven project finance model
A2: Remote-only boundary | B2: GitHub Actions runner only
A3: Synthetic input class | B3: aggregate/synthetic; no private transaction evidence
A4: Formula QA | B4: pending remote reconciliation
A5: External evidence | B5: OPEN_EXTERNAL_GATE
A6: Model role | B6: V4 G4/G5 candidate; not bankability approval

Sheet Assumptions
A1: Assumption | B1: Value
A2: PROJECT_NPV_RATE | B2: 0.12
A3: EQUITY_NPV_RATE | B3: 0.14
A4: DEGRADATION_RATE | B4: 0.005
A5: PPA_ESCALATION | B5: 0.01
A6: ACTIVE_CASE_SWITCH | B6: NEGOTIATED_TERMS
A7: ACTIVE_SCENARIO_SWITCH | B7: BASE_SPONSOR
A8: WORKBOOK_STATUS | B8: FORMULA_DRIVEN_REMOTE_RECALC

Sheet CalcInputs
A1: Case | B1: Project ID | C1: CAPEX VND | D1: Debt VND | E1: Capacity kWp | F1: PVOUT kWh/kWp | G1: PPA VND/kWh | H1: Self-consumed kWh | I1: OPEX VND | J1: CFADS adjustment | K1: Python Project NPV | L1: Python Project IRR | M1: Python Equity NPV | N1: Python Equity IRR | O1: CFADS Y1 | P1: PPA zone
A2: CURRENT_TERMS | B2: VG-001 | C2: 3.1056521e+10 | D2: 1.4555616e+10 | E2: 1400 | F2: 1320 | G2: 2080.75 | H2: 1848000 | I2: 525000000 | J2: 5.9667734e+08 | K2: -1.0492754e+10 | L2: 0.052538067 | M2: -9.6361553e+09 | N2: 0.03697936 | O2: 2.7235487e+09 | P2: EMPTY_ZONE
A3: NEGOTIATED_TERMS | B3: VG-001 | C3: 2.4845217e+10 | D3: 1.6149391e+10 | E3: 1400 | F3: 1320 | G3: 2511.671 | H3: 1848000 | I3: 525000000 | J3: 8.9808126e+08 | K3: -3.7780689e+08 | L3: 0.1172069 | M3: 2.0760583e+08 | N3: 0.14321068 | O3: 3.2184867e+09 | P3: FEASIBLE_ZONE
A4: CURRENT_TERMS | B4: VG-002 | C4: 33274843750 | D4: 1.623884e+10 | E4: 1500 | F4: 1320 | G4: 2163.98 | H4: 1980000 | I4: 562500000 | J4: 6.8580105e+08 | K4: -1.0331627e+10 | L4: 0.058545306 | M4: -9.3758499e+09 | N4: 0.045023907 | O4: 3.0363793e+09 | P4: EMPTY_ZONE
A5: NEGOTIATED_TERMS | B5: VG-002 | C5: 26619875000 | D5: 17302918750 | E5: 1500 | F5: 1320 | G5: 2562.421 | H5: 1980000 | I5: 562500000 | J5: 9.9058596e+08 | K5: 1.5045641e+08 | L5: 0.12103371 | M5: 6.5948437e+08 | N5: 0.14937194 | O5: 3.5205076e+09 | P5: FEASIBLE_ZONE
A6: CURRENT_TERMS | B6: VG-003 | C6: 2.4401552e+10 | D6: 1.163881e+10 | E6: 1100 | F6: 1320 | G6: 2116.42 | H6: 1452000 | I6: 412500000 | J6: 4.8343342e+08 | K6: -7.9581151e+09 | L6: 0.055128051 | M6: -7.2731327e+09 | N6: 0.040410407 | O6: 2.1771084e+09 | P6: EMPTY_ZONE
A7: NEGOTIATED_TERMS | B7: VG-003 | C7: 1.9521242e+10 | D7: 1.2688807e+10 | E7: 1100 | F7: 1320 | G7: 2533.421 | H7: 1452000 | I7: 412500000 | J7: 7.1454717e+08 | K7: -1.2234128e+08 | L7: 0.118851 | M7: 3.004773e+08 | N7: 0.14587462 | O7: 2.5514801e+09 | P7: FEASIBLE_ZONE
A8: CURRENT_TERMS | B8: VG-004 | C8: 3.2165682e+10 | D8: 1.5909965e+10 | E8: 1450 | F8: 1320 | G8: 2192.4 | H8: 1914000 | I8: 543750000 | J8: 6.7829109e+08 | K8: -9.6866644e+09 | L8: 0.060568356 | M8: -8.7502057e+09 | N8: 0.047804201 | O8: 2.9742125e+09 | P8: EMPTY_ZONE
A9: NEGOTIATED_TERMS | B9: VG-004 | C9: 2.5732546e+10 | D9: 1.6726155e+10 | E9: 1450 | F9: 1320 | G9: 2436 | H9: 1914000 | I9: 543750000 | J9: 8.8928456e+08 | K9: -1.1916099e+09 | L9: 0.11143787 | M9: -4.1492182e+08 | N9: 0.13365325 | O9: 3.2294694e+09 | P9: EMPTY_ZONE
A10: CURRENT_TERMS | B10: VG-005 | C10: 26619875000 | D10: 1.5105703e+10 | E10: 1200 | F10: 1480 | G10: 2235.32 | H10: 1775698.1 | I10: 450000000 | J10: 7.0145028e+08 | K10: -5.2730868e+09 | L10: 0.082044505 | M10: -4.3836219e+09 | N10: 0.0800753 | O10: 2.8178032e+09 | P10: FEASIBLE_ZONE
A11: NEGOTIATED_TERMS | B11: VG-005 | C11: 21295900000 | D11: 13842335000 | E11: 1200 | F11: 1480 | G11: 2471.7396 | H11: 1775698.1 | I11: 450000000 | J11: 8.8564526e+08 | K11: 1.9448864e+09 | L11: 0.13642883 | M11: 1.9893467e+09 | N11: 0.17349188 | O11: 3.0534181e+09 | P11: FEASIBLE_ZONE
A12: CURRENT_TERMS | B12: VG-006 | C12: 26619875000 | D12: 1.4118795e+10 | E12: 1200 | F12: 1480 | G12: 2092.64 | H12: 1776000 | I12: 450000000 | J12: 6.301334e+08 | K12: -6.6695674e+09 | L12: 0.071293765 | M12: -5.8383675e+09 | N12: 0.063229458 | O12: 2.6363952e+09 | P12: EMPTY_ZONE
A13: NEGOTIATED_TERMS | B13: VG-006 | C13: 21295900000 | D13: 13842335000 | E13: 1200 | F13: 1480 | G13: 2384.5511 | H13: 1776000 | I13: 450000000 | J13: 8.4215935e+08 | K13: 1.0933738e+09 | L13: 0.1293056 | M13: 1.3017631e+09 | N13: 0.16242762 | O13: 2.9428035e+09 | P13: FEASIBLE_ZONE
... A41: NEGOTIATED_TERMS | B41: VG-020 | C41: 18633912500 | D41: 12112043125 | E41: 1050 | F41: 1420 | G41: 2445.8913 | H41: 1491000 | I41: 393750000 | J41: 7.2030545e+08 | K41: 6.3196524e+08 | L41: 0.12616782 | M41: 8.7682257e+08 | N41: 0.15744413 | O41: 2.5327685e+09 | P41: FEASIBLE_ZONE

Sheet CashFlows
A1: Case | B1: Project ID | C1: Project CF Y1 | D1: Project CF Y2 | E1: Project CF Y3 | F1: Project CF Y4 | G1: Project CF Y5 | H1: Project CF Y6 | I1: Project CF Y7 | J1: Project CF Y8 | K1: Project CF Y9 | L1: Project CF Y10 | M1: Project CF Y11 | N1: Project CF Y12 | O1: Project CF Y13 | P1: Project CF Y14 | Q1: Project CF Y15 | R1: Project CF Y16 | S1: Equity CF Y0 | T1: Equity CF Y1 | U1: Equity CF Y2 | V1: Equity CF Y3 | W1: Equity CF Y4 | X1: Equity CF Y5 | Y1: Equity CF Y6 | Z1: Equity CF Y7 | AA1: Equity CF Y8 | AB1: Equity CF Y9 | AC1: Equity CF Y10 | AD1: Equity CF Y11 | AE1: Equity CF Y12 | AF1: Equity CF Y13 | AG1: Equity CF Y14 | AH1: Equity CF Y15
A2: =CalcInputs!A2 -> CURRENT_TERMS | B2: =CalcInputs!B2 -> VG-001 | C2: =-CalcInputs!C2 -> -3.1056521e+10 | D2: =CalcInputs!O2 -> 2.7235487e+09 | E2: =CalcInputs!P2 -> 3.0448573e+09 | F2: =CalcInputs!Q2 -> 3.051584e+09 | G2: =CalcInputs!R2 -> 3.0582151e+09 | H2: =CalcInputs!S2 -> 2.9209673e+09 | I2: =CalcInputs!T2 -> 3.071178e+09 | J2: =CalcInputs!U2 -> 3.0775036e+09 | K2: =CalcInputs!V2 -> 3.0837208e+09 | ... R2: =CalcInputs!AC2 -> 3.4625883e+09 | S2: =-(CalcInputs!C2-CalcInputs!D2) -> -1.6500905e+10 | T2: =D2-CalcInputs!AD2 -> 6.2851123e+08 | U2: =D2-CalcInputs!AE2 -> 7.0265938e+08 | V2: =D2-CalcInputs!AF2 -> 7.042117e+08 | W2: =D2-CalcInputs!AG2 -> 7.0574195e+08 | X2: =D2-CalcInputs!AH2 -> 6.7406937e+08 | Y2: =D2-CalcInputs!AI2 -> 7.0873339e+08 | Z2: =D2-CalcInputs!AJ2 -> 7.1019313e+08 | AA2: =D2-CalcInputs!AK2 -> 7.1162788e+08 | AB2: =D2-CalcInputs!AL2 -> 7.1303689e+08 | AC2: =D2-CalcInputs!AM2 -> 1.9470088e+09 | AD2: =D2 -> 3.1016894e+09 | AE2: =D2 -> 3.1074396e+09 | AF2: =D2 -> 3.1130642e+09 | AG2: =D2 -> 3.1185594e+09 | AH2: =D2 -> 3.4625883e+09
A3: =CalcInputs!A3 -> NEGOTIATED_TERMS | B3: =CalcInputs!B3 -> VG-001 | C3: =-CalcInputs!C3 -> -2.4845217e+10 | D3: =CalcInputs!O3 -> 3.2184867e+09 | E3: =CalcInputs!P3 -> 3.6080776e+09 | F3: =CalcInputs!Q3 -> 3.6179719e+09 | G3: =CalcInputs!R3 -> 3.6277861e+09 | H3: =CalcInputs!S3 -> 3.5224933e+09 | I3: =CalcInputs!T3 -> 3.6471628e+09 | J3: =CalcInputs!U3 -> 3.656719e+09 | K3: =CalcInputs!V3 -> 3.666183e+09 | ... R3: =CalcInputs!AC3 -> 4.1383693e+09 | S3: =-(CalcInputs!C3-CalcInputs!D3) -> -8.6958258e+09 | T3: =D3-CalcInputs!AD3 -> 7.427277e+08 | U3: =D3-CalcInputs!AE3 -> 8.326333e+08 | V3: =D3-CalcInputs!AF3 -> 8.3491658e+08 | W3: =D3-CalcInputs!AG3 -> 8.3718142e+08 | X3: =D3-CalcInputs!AH3 -> 8.1288307e+08 | Y3: =D3-CalcInputs!AI3 -> 8.4165295e+08 | Z3: =D3-CalcInputs!AJ3 -> 8.4385824e+08 | AA3: =D3-CalcInputs!AK3 -> 8.4604223e+08 | AB3: =D3-CalcInputs!AL3 -> 2.1368186e+09 | AC3: =D3-CalcInputs!AM3 -> 3.5697969e+09 | AD3: =D3 -> 3.6939884e+09 | AE3: =D3 -> 3.7030501e+09 | AF3: =D3 -> 3.7120025e+09 | AG3: =D3 -> 3.720842e+09 | AH3: =D3 -> 4.1383693e+09
A4: =CalcInputs!A4 -> CURRENT_TERMS | B4: =CalcInputs!B4 -> VG-002 | C4: =-CalcInputs!C4 -> -33274843750 | D4: =CalcInputs!O4 -> 3.0363793e+09 | E4: =CalcInputs!P4 -> 3.394769e+09 | F4: =CalcInputs!Q4 -> 3.4026317e+09 | G4: =CalcInputs!R4 -> 3.4103951e+09 | H4: =CalcInputs!S4 -> 3.2640059e+09 | I4: =CalcInputs!T4 -> 3.4256112e+09 | J4: =CalcInputs!U4 -> 3.4330572e+09 | K4: =CalcInputs!V4 -> 3.4403904e+09 | ... R4: =CalcInputs!AC4 -> 3.8656312e+09 | S4: =-(CalcInputs!C4-CalcInputs!D4) -> -1.7036003e+10 | T4: =D4-CalcInputs!AD4 -> 7.0070293e+08 | U4: =D4-CalcInputs!AE4 -> 7.8340823e+08 | V4: =D4-CalcInputs!AF4 -> 7.8522269e+08 | W4: =D4-CalcInputs!AG4 -> 7.8701426e+08 | X4: =D4-CalcInputs!AH4 -> 7.5323213e+08 | Y4: =D4-CalcInputs!AI4 -> 7.9052567e+08 | Z4: =D4-CalcInputs!AJ4 -> 7.9224396e+08 | AA4: =D4-CalcInputs!AK4 -> 7.9393624e+08 | AB4: =D4-CalcInputs!AL4 -> 7.956017e+08 | AC4: =D4-CalcInputs!AM4 -> 2.1738337e+09 | AD4: =D4 -> 3.4616781e+09 | AE4: =D4 -> 3.4685243e+09 | AF4: =D4 -> 3.4752393e+09 | AG4: =D4 -> 3.4818191e+09 | AH4: =D4 -> 3.8656312e+09
A5: =CalcInputs!A5 -> NEGOTIATED_TERMS | B5: =CalcInputs!B5 -> VG-002 | C5: =-CalcInputs!C5 -> -26619875000 | D5: =CalcInputs!O5 -> 3.5205076e+09 | E5: =CalcInputs!P5 -> 3.9465425e+09 | F5: =CalcInputs!Q5 -> 3.9575432e+09 | G5: =CalcInputs!R5 -> 3.9684601e+09 | H5: =CalcInputs!S5 -> 3.85605e+09 | I5: =CalcInputs!T5 -> 3.9900301e+09 | J5: =CalcInputs!U5 -> 4.0006766e+09 | K5: =CalcInputs!V5 -> 4.0112263e+09 | ... R5: =CalcInputs!AC5 -> 4.5289154e+09 | S5: =-(CalcInputs!C5-CalcInputs!D5) -> -9316956250 | T5: =D5-CalcInputs!AD5 -> 8.1242482e+08 | U5: =D5-CalcInputs!AE5 -> 9.1074057e+08 | V5: =D5-CalcInputs!AF5 -> 9.1327919e+08 | W5: =D5-CalcInputs!AG5 -> 9.1579849e+08 | X5: =D5-CalcInputs!AH5 -> 8.898577e+08 | Y5: =D5-CalcInputs!AI5 -> 9.2077618e+08 | Z5: =D5-CalcInputs!AJ5 -> 9.2323307e+08 | AA5: =D5-CalcInputs!AK5 -> 9.256676e+08 | AB5: =D5-CalcInputs!AL5 -> 3.0983419e+09 | AC5: =D5-CalcInputs!AM5 -> 3.9087809e+09 | AD5: =D5 -> 4.042259e+09 | AE5: =D5 -> 4.0523858e+09 | AF5: =D5 -> 4.0623976e+09 | AG5: =D5 -> 4.0722905e+09 | AH5: =D5 -> 4.5289154e+09
A6: =CalcInputs!A6 -> CURRENT_TERMS | B6: =CalcInputs!B6 -> VG-003 | C6: =-CalcInputs!C6 -> -2.4401552e+10 | D6: =CalcInputs!O6 -> 2.1771084e+09 | E6: =CalcInputs!P6 -> 2.4340062e+09 | F6: =CalcInputs!Q6 -> 2.4394975e+09 | G6: =CalcInputs!R6 -> 2.4449146e+09 | H6: =CalcInputs!S6 -> 2.3372851e+09 | I6: =CalcInputs!T6 -> 2.4555169e+09 | J6: =CalcInputs!U6 -> 2.4606971e+09 | K6: =CalcInputs!V6 -> 2.4657933e+09 | ... R6: =CalcInputs!AC6 -> 2.7695441e+09 | S6: =-(CalcInputs!C6-CalcInputs!D6) -> -1.2762742e+10 | T6: =D6-CalcInputs!AD6 -> 5.0240964e+08 | U6: =D6-CalcInputs!AE6 -> 5.6169373e+08 | V6: =D6-CalcInputs!AF6 -> 5.6296096e+08 | W6: =D6-CalcInputs!AG6 -> 5.6421107e+08 | X6: =D6-CalcInputs!AH6 -> 5.3937349e+08 | Y6: =D6-CalcInputs!AI6 -> 5.6665775e+08 | Z6: =D6-CalcInputs!AJ6 -> 5.6785318e+08 | AA6: =D6-CalcInputs!AK6 -> 5.6902922e+08 | AB6: =D6-CalcInputs!AL6 -> 5.7018526e+08 | AC6: =D6-CalcInputs!AM6 -> 1.5573721e+09 | AD6: =D6 -> 2.4805512e+09 | AE6: =D6 -> 2.4852846e+09 | AF6: =D6 -> 2.4899203e+09 | AG6: =D6 -> 2.4944555e+09 | AH6: =D6 -> 2.7695441e+09
A7: =CalcInputs!A7 -> NEGOTIATED_TERMS | B7: =CalcInputs!B7 -> VG-003 | C7: =-CalcInputs!C7 -> -1.9521242e+10 | D7: =CalcInputs!O7 -> 2.5514801e+09 | E7: =CalcInputs!P7 -> 2.8602951e+09 | F7: =CalcInputs!Q7 -> 2.8681948e+09 | G7: =CalcInputs!R7 -> 2.8760323e+09 | H7: =CalcInputs!S7 -> 2.793429e+09 | I7: =CalcInputs!T7 -> 2.8915111e+09 | J7: =CalcInputs!U7 -> 2.8991477e+09 | K7: =CalcInputs!V7 -> 2.9067125e+09 | ... R7: =CalcInputs!AC7 -> 3.2814168e+09 | S7: =-(CalcInputs!C7-CalcInputs!D7) -> -6.8324346e+09 | T7: =D7-CalcInputs!AD7 -> 5.8880309e+08 | U7: =D7-CalcInputs!AE7 -> 6.6006811e+08 | V7: =D7-CalcInputs!AF7 -> 6.6189111e+08 | W7: =D7-CalcInputs!AG7 -> 6.6369975e+08 | X7: =D7-CalcInputs!AH7 -> 6.4463747e+08 | Y7: =D7-CalcInputs!AI7 -> 6.672718e+08 | Z7: =D7-CalcInputs!AJ7 -> 6.6903409e+08 | AA7: =D7-CalcInputs!AK7 -> 6.707798e+08 | AB7: =D7-CalcInputs!AL7 -> 1.9331525e+09 | AC7: =D7-CalcInputs!AM7 -> 2.83124e+09 | AD7: =D7 -> 2.9289497e+09 | AE7: =D7 -> 2.9362009e+09 | AF7: =D7 -> 2.9433669e+09 | AG7: =D7 -> 2.9504449e+09 | AH7: =D7 -> 3.2814168e+09
A8: =CalcInputs!A8 -> CURRENT_TERMS | B8: =CalcInputs!B8 -> VG-004 | C8: =-CalcInputs!C8 -> -3.2165682e+10 | D8: =CalcInputs!O8 -> 2.9742125e+09 | E8: =CalcInputs!P8 -> 3.32532e+09 | F8: =CalcInputs!Q8 -> 3.333137e+09 | G8: =CalcInputs!R8 -> 3.3408591e+09 | H8: =CalcInputs!S8 -> 3.199568e+09 | I8: =CalcInputs!T8 -> 3.3560061e+09 | J8: =CalcInputs!U8 -> 3.3634245e+09 | K8: =CalcInputs!V8 -> 3.370735e+09 | ... R8: =CalcInputs!AC8 -> 3.7881755e+09 | S8: =-(CalcInputs!C8-CalcInputs!D8) -> -1.6255717e+10 | T8: =D8-CalcInputs!AD8 -> 6.8635673e+08 | U8: =D8-CalcInputs!AE8 -> 7.6738154e+08 | V8: =D8-CalcInputs!AF8 -> 7.6918545e+08 | W8: =D8-CalcInputs!AG8 -> 7.7096748e+08 | X8: =D8-CalcInputs!AH8 -> 7.3836184e+08 | Y8: =D8-CalcInputs!AI8 -> 7.7446294e+08 | Z8: =D8-CalcInputs!AJ8 -> 7.7617488e+08 | AA8: =D8-CalcInputs!AK8 -> 7.7786193e+08 | AB8: =D8-CalcInputs!AL8 -> 7.7952331e+08 | AC8: =D8-CalcInputs!AM8 -> 2.1303381e+09 | AD8: =D8 -> 3.3919851e+09 | AE8: =D8 -> 3.3988293e+09 | AF8: =D8 -> 3.4055477e+09 | AG8: =D8 -> 3.4121366e+09 | AH8: =D8 -> 3.7881755e+09
A9: =CalcInputs!A9 -> NEGOTIATED_TERMS | B9: =CalcInputs!B9 -> VG-004 | C9: =-CalcInputs!C9 -> -2.5732546e+10 | D9: =CalcInputs!O9 -> 3.2294694e+09 | E9: =CalcInputs!P9 -> 3.6205555e+09 | F9: =CalcInputs!Q9 -> 3.6302271e+09 | G9: =CalcInputs!R9 -> 3.6398129e+09 | H9: =CalcInputs!S9 -> 3.5301778e+09 | I9: =CalcInputs!T9 -> 3.6587151e+09 | J9: =CalcInputs!U9 -> 3.668025e+09 | K9: =CalcInputs!V9 -> 3.6772365e+09 | ... R9: =CalcInputs!AC9 -> 4.1493143e+09 | S9: =-(CalcInputs!C9-CalcInputs!D9) -> -9.006391e+09 | T9: =D9-CalcInputs!AD9 -> 7.4526218e+08 | U9: =D9-CalcInputs!AE9 -> 8.3551281e+08 | V9: =D9-CalcInputs!AF9 -> 8.377447e+08 | W9: =D9-CalcInputs!AG9 -> 8.3995682e+08 | X9: =D9-CalcInputs!AH9 -> 8.1465642e+08 | Y9: =D9-CalcInputs!AI9 -> 8.4431887e+08 | Z9: =D9-CalcInputs!AJ9 -> 8.4646732e+08 | AA9: =D9-CalcInputs!AK9 -> 8.4859304e+08 | AB9: =D9-CalcInputs!AL9 -> 1.0472336e+09 | AC9: =D9-CalcInputs!AM9 -> 3.5762183e+09 | AD9: =D9 -> 3.7042459e+09 | AE9: =D9 -> 3.7130289e+09 | AF9: =D9 -> 3.7216958e+09 | AG9: =D9 -> 3.7302428e+09 | AH9: =D9 -> 4.1493143e+09
A10: =CalcInputs!A10 -> CURRENT_TERMS | B10: =CalcInputs!B10 -> VG-005 | C10: =-CalcInputs!C10 -> -26619875000 | D10: =CalcInputs!O10 -> 2.8178032e+09 | E10: =CalcInputs!P10 -> 3.1509466e+09 | F10: =CalcInputs!Q10 -> 3.1593907e+09 | G10: =CalcInputs!R10 -> 3.167766e+09 | H10: =CalcInputs!S10 -> 3.0528299e+09 | I10: =CalcInputs!T10 -> 3.1843002e+09 | J10: =CalcInputs!U10 -> 3.1924538e+09 | K10: =CalcInputs!V10 -> 3.2005281e+09 | ... R10: =CalcInputs!AC10 -> 3.6041772e+09 | S10: =-(CalcInputs!C10-CalcInputs!D10) -> -1.1514172e+10 | T10: =D10-CalcInputs!AD10 -> 6.5026228e+08 | U10: =D10-CalcInputs!AE10 -> 7.2714152e+08 | V10: =D10-CalcInputs!AF10 -> 7.2909015e+08 | W10: =D10-CalcInputs!AG10 -> 7.3102292e+08 | X10: =D10-CalcInputs!AH10 -> 7.044992e+08 | Y10: =D10-CalcInputs!AI10 -> 7.348385e+08 | Z10: =D10-CalcInputs!AJ10 -> 7.3672011e+08 | AA10: =D10-CalcInputs!AK10 -> 7.3858341e+08 | AB10: =D10-CalcInputs!AL10 -> 7.4042778e+08 | AC10: =D10-CalcInputs!AM10 -> 2.027418e+09 | AD10: =D10 -> 3.2242473e+09 | AE10: =D10 -> 3.231976e+09 | AF10: =D10 -> 3.2396109e+09 | AG10: =D10 -> 3.2471489e+09 | AH10: =D10 -> 3.6041772e+09
A11: =CalcInputs!A11 -> NEGOTIATED_TERMS | B11: =CalcInputs!B11 -> VG-005 | C11: =-CalcInputs!C11 -> -21295900000 | D11: =CalcInputs!O11 -> 3.0534181e+09 | E11: =CalcInputs!P11 -> 3.422558e+09 | F11: =CalcInputs!Q11 -> 3.4326719e+09 | G11: =CalcInputs!R11 -> 3.4427253e+09 | H11: =CalcInputs!S11 -> 3.3541237e+09 | I11: =CalcInputs!T11 -> 3.4626407e+09 | J11: =CalcInputs!U11 -> 3.4724974e+09 | K11: =CalcInputs!V11 -> 3.4822833e+09 | ... R11: =CalcInputs!AC11 -> 3.9351276e+09 | S11: =-(CalcInputs!C11-CalcInputs!D11) -> -7453565000 | T11: =D11-CalcInputs!AD11 -> 7.0463494e+08 | U11: =D11-CalcInputs!AE11 -> 7.8982108e+08 | V11: =D11-CalcInputs!AF11 -> 7.9215506e+08 | W11: =D11-CalcInputs!AG11 -> 7.9447508e+08 | X11: =D11-CalcInputs!AH11 -> 7.7402854e+08 | Y11: =D11-CalcInputs!AI11 -> 7.9907093e+08 | Z11: =D11-CalcInputs!AJ11 -> 8.0134556e+08 | AA11: =D11-CalcInputs!AK11 -> 2.3194194e+09 | AB11: =D11-CalcInputs!AL11 -> 3.4919956e+09 | AC11: =D11-CalcInputs!AM11 -> 3.4030394e+09 | AD11: =D11 -> 3.5111882e+09 | AE11: =D11 -> 3.5206627e+09 | AF11: =D11 -> 3.5300519e+09 | AG11: =D11 -> 3.5393529e+09 | AH11: =D11 -> 3.9351276e+09
A12: =CalcInputs!A12 -> CURRENT_TERMS | B12: =CalcInputs!B12 -> VG-006 | C12: =-CalcInputs!C12 -> -26619875000 | D12: =CalcInputs!O12 -> 2.6363952e+09 | E12: =CalcInputs!P12 -> 2.9478687e+09 | F12: =CalcInputs!Q12 -> 2.9553076e+09 | G12: =CalcInputs!R12 -> 2.9626727e+09 | H12: =CalcInputs!S12 -> 2.8467213e+09 | I12: =CalcInputs!T12 -> 2.9771714e+09 | J12: =CalcInputs!U12 -> 2.9842997e+09 | K12: =CalcInputs!V12 -> 2.9913437e+09 | ... R12: =CalcInputs!AC12 -> 3.3653774e+09 | S12: =-(CalcInputs!C12-CalcInputs!D12) -> -1.250108e+10 | T12: =D12-CalcInputs!AD12 -> 6.083989e+08 | U12: =D12-CalcInputs!AE12 -> 6.802774e+08 | V12: =D12-CalcInputs!AF12 -> 6.8199405e+08 | W12: =D12-CalcInputs!AG12 -> 6.8369369e+08 | X12: =D12-CalcInputs!AH12 -> 6.5693569e+08 | Y12: =D12-CalcInputs!AI12 -> 6.8703956e+08 | Z12: =D12-CalcInputs!AJ12 -> 6.8868456e+08 | AA12: =D12-CalcInputs!AK12 -> 6.9031009e+08 | AB12: =D12-CalcInputs!AL12 -> 6.919155e+08 | AC12: =D12-CalcInputs!AM12 -> 1.8928432e+09 | AD12: =D12 -> 3.0119411e+09 | AE12: =D12 -> 3.0186189e+09 | AF12: =D12 -> 3.0251977e+09 | AG12: =D12 -> 3.0316743e+09 | AH12: =D12 -> 3.3653774e+09
A13: =CalcInputs!A13 -> NEGOTIATED_TERMS | B13: =CalcInputs!B13 -> VG-006 | C13: =-CalcInputs!C13 -> -21295900000 | D13: =CalcInputs!O13 -> 2.9428035e+09 | E13: =CalcInputs!P13 -> 3.2987301e+09 | F13: =CalcInputs!Q13 -> 3.308231e+09 | G13: =CalcInputs!R13 -> 3.3176684e+09 | H13: =CalcInputs!S13 -> 3.2284477e+09 | I13: =CalcInputs!T13 -> 3.3363427e+09 | J13: =CalcInputs!U13 -> 3.3455742e+09 | K13: =CalcInputs!V13 -> 3.3547319e+09 | ... R13: =CalcInputs!AC13 -> 3.789518e+09 | S13: =-(CalcInputs!C13-CalcInputs!D13) -> -7453565000 | T13: =D13-CalcInputs!AD13 -> 6.7910849e+08 | U13: =D13-CalcInputs!AE13 -> 7.612454e+08 | V13: =D13-CalcInputs!AF13 -> 7.6343792e+08 | W13: =D13-CalcInputs!AG13 -> 7.6561579e+08 | X13: =D13-CalcInputs!AH13 -> 7.450264e+08 | Y13: =D13-CalcInputs!AI13 -> 7.6992523e+08 | Z13: =D13-CalcInputs!AJ13 -> 7.7205559e+08 | AA13: =D13-CalcInputs!AK13 -> 1.2648141e+09 | AB13: =D13-CalcInputs!AL13 -> 3.3638128e+09 | AC13: =D13-CalcInputs!AM13 -> 3.2742221e+09 | AD13: =D13 -> 3.3817332e+09 | AE13: =D13 -> 3.3905669e+09 | AF13: =D13 -> 3.3993121e+09 | AG13: =D13 -> 3.407966e+09 | AH13: =D13 -> 3.789518e+09
... A41: =CalcInputs!A41 -> NEGOTIATED_TERMS | B41: =CalcInputs!B41 -> VG-020 | C41: =-CalcInputs!C41 -> -18633912500 | D41: =CalcInputs!O41 -> 2.5327685e+09 | E41: =CalcInputs!P41 -> 2.8391652e+09 | F41: =CalcInputs!Q41 -> 2.8472448e+09 | G41: =CalcInputs!R41 -> 2.8552676e+09 | H41: =CalcInputs!S41 -> 2.7769634e+09 | I41: =CalcInputs!T41 -> 2.8711342e+09 | J41: =CalcInputs!U41 -> 2.8789734e+09 | K41: =CalcInputs!V41 -> 2.8867468e+09 | ... R41: =CalcInputs!AC41 -> 3.2602978e+09 | S41: =-(CalcInputs!C41-CalcInputs!D41) -> -6521869375 | T41: =D41-CalcInputs!AD41 -> 5.8448504e+08 | U41: =D41-CalcInputs!AE41 -> 6.5519197e+08 | V41: =D41-CalcInputs!AF41 -> 6.5705648e+08 | W41: =D41-CalcInputs!AG41 -> 6.5890791e+08 | X41: =D41-CalcInputs!AH41 -> 6.4083771e+08 | Y41: =D41-CalcInputs!AI41 -> 6.6256944e+08 | Z41: =D41-CalcInputs!AJ41 -> 6.6437848e+08 | AA41: =D41-CalcInputs!AK41 -> 7.0452317e+08 | AB41: =D41-CalcInputs!AL41 -> 2.8944518e+09 | AC41: =D41-CalcInputs!AM41 -> 2.8158179e+09 | AD41: =D41 -> 2.909647e+09 | AE41: =D41 -> 2.9171321e+09 | AF41: =D41 -> 2.9245386e+09 | AG41: =D41 -> 2.9318639e+09 | AH41: =D41 -> 3.2602978e+09

Sheet Returns
A1: Case | B1: Project ID | C1: P50 Energy | D1: Self-consumed kWh | E1: PPA VND/kWh | F1: Revenue Y1 | G1: OPEX Y1 | H1: CFADS Y1 | I1: CAPEX | J1: Debt | K1: Equity Required | L1: Project NPV | M1: Project IRR | N1: Equity NPV | O1: Equity IRR | P1: PPA Zone | Q1: Formula Gate
A2: =CalcInputs!A2 -> CURRENT_TERMS | B2: =CalcInputs!B2 -> VG-001 | C2: =CalcInputs!E2*CalcInputs!F2 -> 1848000 | D2: =CalcInputs!H2 -> 1848000 | E2: =CalcInputs!G2 -> 2080.75 | F2: =D2*E2 -> 3845226000 | G2: =CalcInputs!I2 -> 525000000 | H2: =F2-G2-CalcInputs!J2 -> 2.7235487e+09 | I2: =CalcInputs!C2 -> 3.1056521e+10 | J2: =CalcInputs!D2 -> 1.4555616e+10 | K2: =I2-J2 -> 1.6500905e+10 | L2: =-I2+NPV(Assumptions!$B$2,CashFlows!D2:R2) -> -1.0492754e+10 | M2: =IRR(CashFlows!C2:R2) -> 0.052538067 | N2: =-K2+NPV(Assumptions!$B$3,CashFlows!T2:AH2) -> -9.6361553e+09 | O2: =IRR(CashFlows!S2:AH2) -> 0.03697936 | P2: =CalcInputs!P2 -> EMPTY_ZONE | Q2: =IF(AND(N2>0,J2>=0),"PASS","CHECK") -> CHECK
A3: =CalcInputs!A3 -> NEGOTIATED_TERMS | B3: =CalcInputs!B3 -> VG-001 | C3: =CalcInputs!E3*CalcInputs!F3 -> 1848000 | D3: =CalcInputs!H3 -> 1848000 | E3: =CalcInputs!G3 -> 2511.671 | F3: =D3*E3 -> 4.6415679e+09 | G3: =CalcInputs!I3 -> 525000000 | H3: =F3-G3-CalcInputs!J3 -> 3.2184867e+09 | I3: =CalcInputs!C3 -> 2.4845217e+10 | J3: =CalcInputs!D3 -> 1.6149391e+10 | K3: =I3-J3 -> 8.6958258e+09 | L3: =-I3+NPV(Assumptions!$B$2,CashFlows!D3:R3) -> -3.7780689e+08 | M3: =IRR(CashFlows!C3:R3) -> 0.1172069 | N3: =-K3+NPV(Assumptions!$B$3,CashFlows!T3:AH3) -> 2.0760583e+08 | O3: =IRR(CashFlows!S3:AH3) -> 0.14321068 | P3: =CalcInputs!P3 -> FEASIBLE_ZONE | Q3: =IF(AND(N3>0,J3>=0),"PASS","CHECK") -> PASS
A4: =CalcInputs!A4 -> CURRENT_TERMS | B4: =CalcInputs!B4 -> VG-002 | C4: =CalcInputs!E4*CalcInputs!F4 -> 1980000 | D4: =CalcInputs!H4 -> 1980000 | E4: =CalcInputs!G4 -> 2163.98 | F4: =D4*E4 -> 4284680400 | G4: =CalcInputs!I4 -> 562500000 | H4: =F4-G4-CalcInputs!J4 -> 3.0363793e+09 | I4: =CalcInputs!C4 -> 33274843750 | J4: =CalcInputs!D4 -> 1.623884e+10 | K4: =I4-J4 -> 1.7036003e+10 | L4: =-I4+NPV(Assumptions!$B$2,CashFlows!D4:R4) -> -1.0331627e+10 | M4: =IRR(CashFlows!C4:R4) -> 0.058545306 | N4: =-K4+NPV(Assumptions!$B$3,CashFlows!T4:AH4) -> -9.3758499e+09 | O4: =IRR(CashFlows!S4:AH4) -> 0.045023907 | P4: =CalcInputs!P4 -> EMPTY_ZONE | Q4: =IF(AND(N4>0,J4>=0),"PASS","CHECK") -> CHECK
A5: =CalcInputs!A5 -> NEGOTIATED_TERMS | B5: =CalcInputs!B5 -> VG-002 | C5: =CalcInputs!E5*CalcInputs!F5 -> 1980000 | D5: =CalcInputs!H5 -> 1980000 | E5: =CalcInputs!G5 -> 2562.421 | F5: =D5*E5 -> 5.0735935e+09 | G5: =CalcInputs!I5 -> 562500000 | H5: =F5-G5-CalcInputs!J5 -> 3.5205076e+09 | I5: =CalcInputs!C5 -> 26619875000 | J5: =CalcInputs!D5 -> 17302918750 | K5: =I5-J5 -> 9316956250 | L5: =-I5+NPV(Assumptions!$B$2,CashFlows!D5:R5) -> 1.5045641e+08 | M5: =IRR(CashFlows!C5:R5) -> 0.12103371 | N5: =-K5+NPV(Assumptions!$B$3,CashFlows!T5:AH5) -> 6.5948437e+08 | O5: =IRR(CashFlows!S5:AH5) -> 0.14937194 | P5: =CalcInputs!P5 -> FEASIBLE_ZONE | Q5: =IF(AND(N5>0,J5>=0),"PASS","CHECK") -> PASS
A6: =CalcInputs!A6 -> CURRENT_TERMS | B6: =CalcInputs!B6 -> VG-003 | C6: =CalcInputs!E6*CalcInputs!F6 -> 1452000 | D6: =CalcInputs!H6 -> 1452000 | E6: =CalcInputs!G6 -> 2116.42 | F6: =D6*E6 -> 3073041840 | G6: =CalcInputs!I6 -> 412500000 | H6: =F6-G6-CalcInputs!J6 -> 2.1771084e+09 | I6: =CalcInputs!C6 -> 2.4401552e+10 | J6: =CalcInputs!D6 -> 1.163881e+10 | K6: =I6-J6 -> 1.2762742e+10 | L6: =-I6+NPV(Assumptions!$B$2,CashFlows!D6:R6) -> -7.9581151e+09 | M6: =IRR(CashFlows!C6:R6) -> 0.055128051 | N6: =-K6+NPV(Assumptions!$B$3,CashFlows!T6:AH6) -> -7.2731327e+09 | O6: =IRR(CashFlows!S6:AH6) -> 0.040410407 | P6: =CalcInputs!P6 -> EMPTY_ZONE | Q6: =IF(AND(N6>0,J6>=0),"PASS","CHECK") -> CHECK
A7: =CalcInputs!A7 -> NEGOTIATED_TERMS | B7: =CalcInputs!B7 -> VG-003 | C7: =CalcInputs!E7*CalcInputs!F7 -> 1452000 | D7: =CalcInputs!H7 -> 1452000 | E7: =CalcInputs!G7 -> 2533.421 | F7: =D7*E7 -> 3.6785272e+09 | G7: =CalcInputs!I7 -> 412500000 | H7: =F7-G7-CalcInputs!J7 -> 2.5514801e+09 | I7: =CalcInputs!C7 -> 1.9521242e+10 | J7: =CalcInputs!D7 -> 1.2688807e+10 | K7: =I7-J7 -> 6.8324346e+09 | L7: =-I7+NPV(Assumptions!$B$2,CashFlows!D7:R7) -> -1.2234128e+08 | M7: =IRR(CashFlows!C7:R7) -> 0.118851 | N7: =-K7+NPV(Assumptions!$B$3,CashFlows!T7:AH7) -> 3.004773e+08 | O7: =IRR(CashFlows!S7:AH7) -> 0.14587462 | P7: =CalcInputs!P7 -> FEASIBLE_ZONE | Q7: =IF(AND(N7>0,J7>=0),"PASS","CHECK") -> PASS
A8: =CalcInputs!A8 -> CURRENT_TERMS | B8: =CalcInputs!B8 -> VG-004 | C8: =CalcInputs!E8*CalcInputs!F8 -> 1914000 | D8: =CalcInputs!H8 -> 1914000 | E8: =CalcInputs!G8 -> 2192.4 | F8: =D8*E8 -> 4196253600 | G8: =CalcInputs!I8 -> 543750000 | H8: =F8-G8-CalcInputs!J8 -> 2.9742125e+09 | I8: =CalcInputs!C8 -> 3.2165682e+10 | J8: =CalcInputs!D8 -> 1.5909965e+10 | K8: =I8-J8 -> 1.6255717e+10 | L8: =-I8+NPV(Assumptions!$B$2,CashFlows!D8:R8) -> -9.6866644e+09 | M8: =IRR(CashFlows!C8:R8) -> 0.060568356 | N8: =-K8+NPV(Assumptions!$B$3,CashFlows!T8:AH8) -> -8.7502057e+09 | O8: =IRR(CashFlows!S8:AH8) -> 0.047804201 | P8: =CalcInputs!P8 -> EMPTY_ZONE | Q8: =IF(AND(N8>0,J8>=0),"PASS","CHECK") -> CHECK
A9: =CalcInputs!A9 -> NEGOTIATED_TERMS | B9: =CalcInputs!B9 -> VG-004 | C9: =CalcInputs!E9*CalcInputs!F9 -> 1914000 | D9: =CalcInputs!H9 -> 1914000 | E9: =CalcInputs!G9 -> 2436 | F9: =D9*E9 -> 4.662504e+09 | G9: =CalcInputs!I9 -> 543750000 | H9: =F9-G9-CalcInputs!J9 -> 3.2294694e+09 | I9: =CalcInputs!C9 -> 2.5732546e+10 | J9: =CalcInputs!D9 -> 1.6726155e+10 | K9: =I9-J9 -> 9.006391e+09 | L9: =-I9+NPV(Assumptions!$B$2,CashFlows!D9:R9) -> -1.1916099e+09 | M9: =IRR(CashFlows!C9:R9) -> 0.11143787 | N9: =-K9+NPV(Assumptions!$B$3,CashFlows!T9:AH9) -> -4.1492182e+08 | O9: =IRR(CashFlows!S9:AH9) -> 0.13365325 | P9: =CalcInputs!P9 -> EMPTY_ZONE | Q9: =IF(AND(N9>0,J9>=0),"PASS","CHECK") -> CHECK
A10: =CalcInputs!A10 -> CURRENT_TERMS | B10: =CalcInputs!B10 -> VG-005 | C10: =CalcInputs!E10*CalcInputs!F10 -> 1776000 | D10: =CalcInputs!H10 -> 1775698.1 | E10: =CalcInputs!G10 -> 2235.32 | F10: =D10*E10 -> 3.9692535e+09 | G10: =CalcInputs!I10 -> 450000000 | H10: =F10-G10-CalcInputs!J10 -> 2.8178032e+09 | I10: =CalcInputs!C10 -> 26619875000 | J10: =CalcInputs!D10 -> 1.5105703e+10 | K10: =I10-J10 -> 1.1514172e+10 | L10: =-I10+NPV(Assumptions!$B$2,CashFlows!D10:R10) -> -5.2730868e+09 | M10: =IRR(CashFlows!C10:R10) -> 0.082044505 | N10: =-K10+NPV(Assumptions!$B$3,CashFlows!T10:AH10) -> -4.3836219e+09 | O10: =IRR(CashFlows!S10:AH10) -> 0.0800753 | P10: =CalcInputs!P10 -> FEASIBLE_ZONE | Q10: =IF(AND(N10>0,J10>=0),"PASS","CHECK") -> CHECK
A11: =CalcInputs!A11 -> NEGOTIATED_TERMS | B11: =CalcInputs!B11 -> VG-005 | C11: =CalcInputs!E11*CalcInputs!F11 -> 1776000 | D11: =CalcInputs!H11 -> 1775698.1 | E11: =CalcInputs!G11 -> 2471.7396 | F11: =D11*E11 -> 4.3890633e+09 | G11: =CalcInputs!I11 -> 450000000 | H11: =F11-G11-CalcInputs!J11 -> 3.0534181e+09 | I11: =CalcInputs!C11 -> 21295900000 | J11: =CalcInputs!D11 -> 13842335000 | K11: =I11-J11 -> 7453565000 | L11: =-I11+NPV(Assumptions!$B$2,CashFlows!D11:R11) -> 1.9448864e+09 | M11: =IRR(CashFlows!C11:R11) -> 0.13642883 | N11: =-K11+NPV(Assumptions!$B$3,CashFlows!T11:AH11) -> 1.9893467e+09 | O11: =IRR(CashFlows!S11:AH11) -> 0.17349188 | P11: =CalcInputs!P11 -> FEASIBLE_ZONE | Q11: =IF(AND(N11>0,J11>=0),"PASS","CHECK") -> PASS
A12: =CalcInputs!A12 -> CURRENT_TERMS | B12: =CalcInputs!B12 -> VG-006 | C12: =CalcInputs!E12*CalcInputs!F12 -> 1776000 | D12: =CalcInputs!H12 -> 1776000 | E12: =CalcInputs!G12 -> 2092.64 | F12: =D12*E12 -> 3716528640 | G12: =CalcInputs!I12 -> 450000000 | H12: =F12-G12-CalcInputs!J12 -> 2.6363952e+09 | I12: =CalcInputs!C12 -> 26619875000 | J12: =CalcInputs!D12 -> 1.4118795e+10 | K12: =I12-J12 -> 1.250108e+10 | L12: =-I12+NPV(Assumptions!$B$2,CashFlows!D12:R12) -> -6.6695674e+09 | M12: =IRR(CashFlows!C12:R12) -> 0.071293765 | N12: =-K12+NPV(Assumptions!$B$3,CashFlows!T12:AH12) -> -5.8383675e+09 | O12: =IRR(CashFlows!S12:AH12) -> 0.063229458 | P12: =CalcInputs!P12 -> EMPTY_ZONE | Q12: =IF(AND(N12>0,J12>=0),"PASS","CHECK") -> CHECK
A13: =CalcInputs!A13 -> NEGOTIATED_TERMS | B13: =CalcInputs!B13 -> VG-006 | C13: =CalcInputs!E13*CalcInputs!F13 -> 1776000 | D13: =CalcInputs!H13 -> 1776000 | E13: =CalcInputs!G13 -> 2384.5511 | F13: =D13*E13 -> 4.2349628e+09 | G13: =CalcInputs!I13 -> 450000000 | H13: =F13-G13-CalcInputs!J13 -> 2.9428035e+09 | I13: =CalcInputs!C13 -> 21295900000 | J13: =CalcInputs!D13 -> 13842335000 | K13: =I13-J13 -> 7453565000 | L13: =-I13+NPV(Assumptions!$B$2,CashFlows!D13:R13) -> 1.0933738e+09 | M13: =IRR(CashFlows!C13:R13) -> 0.1293056 | N13: =-K13+NPV(Assumptions!$B$3,CashFlows!T13:AH13) -> 1.3017631e+09 | O13: =IRR(CashFlows!S13:AH13) -> 0.16242762 | P13: =CalcInputs!P13 -> FEASIBLE_ZONE | Q13: =IF(AND(N13>0,J13>=0),"PASS","CHECK") -> PASS
... A41: =CalcInputs!A41 -> NEGOTIATED_TERMS | B41: =CalcInputs!B41 -> VG-020 | C41: =CalcInputs!E41*CalcInputs!F41 -> 1491000 | D41: =CalcInputs!H41 -> 1491000 | E41: =CalcInputs!G41 -> 2445.8913 | F41: =D41*E41 -> 3.646824e+09 | G41: =CalcInputs!I41 -> 393750000 | H41: =F41-G41-CalcInputs!J41 -> 2.5327685e+09 | I41: =CalcInputs!C41 -> 18633912500 | J41: =CalcInputs!D41 -> 12112043125 | K41: =I41-J41 -> 6521869375 | L41: =-I41+NPV(Assumptions!$B$2,CashFlows!D41:R41) -> 6.3196524e+08 | M41: =IRR(CashFlows!C41:R41) -> 0.12616782 | N41: =-K41+NPV(Assumptions!$B$3,CashFlows!T41:AH41) -> 8.7682257e+08 | O41: =IRR(CashFlows!S41:AH41) -> 0.15744413 | P41: =CalcInputs!P41 -> FEASIBLE_ZONE | Q41: =IF(AND(N41>0,J41>=0),"PASS","CHECK") -> PASS

Sheet Scenarios
A1: Scenario | B1: Selected Count | C1: Project NPV | D1: Equity NPV | E1: Min DSCR | F1: Switch Status
A2: BASE_SPONSOR | B2: 4 | C2: 5.2623925e+09 | D2: 5.9422768e+09 | E2: 1.3 | F2: =IF(A2=Assumptions!$B$7,"ACTIVE","AVAILABLE") -> ACTIVE
A3: P90_ENERGY | B3: 4 | C3: -3.7296847e+09 | D3: -1.1778961e+09 | E3: 1.3 | F3: =IF(A3=Assumptions!$B$7,"ACTIVE","AVAILABLE") -> AVAILABLE
A4: CAPEX_OVERRUN | B4: 4 | C4: -6.6158198e+09 | D4: -3.1791596e+09 | E4: 1.3 | F4: =IF(A4=Assumptions!$B$7,"ACTIVE","AVAILABLE") -> AVAILABLE
A5: COD_DELAY | B5: 4 | C5: -7.0452109e+09 | D5: -4.7923928e+09 | E5: 0 | F5: =IF(A5=Assumptions!$B$7,"ACTIVE","AVAILABLE") -> AVAILABLE
A6: INTEREST_RATE_SHOCK | B6: 4 | C6: 5.2623925e+09 | D6: 2.1047255e+09 | E6: 1.3 | F6: =IF(A6=Assumptions!$B$7,"ACTIVE","AVAILABLE") -> AVAILABLE
A7: DSO_DELAY | B7: 4 | C7: 3.1984203e+09 | D7: 4.3944231e+09 | E7: 1.3 | F7: =IF(A7=Assumptions!$B$7,"ACTIVE","AVAILABLE") -> AVAILABLE
A8: COMBINED_DOWNSIDE | B8: 4 | C8: -3.595699e+10 | D8: -3.8814456e+10 | E8: 0 | F8: =IF(A8=Assumptions!$B$7,"ACTIVE","AVAILABLE") -> AVAILABLE

Sheet Dashboard
A1: V4 decision dashboard
A2: Formula-driven; recalculated remotely
A3: Active case switch | B3: =Assumptions!B6 -> NEGOTIATED_TERMS
A4: Active scenario switch | B4: =Assumptions!B7 -> BASE_SPONSOR
A6: Current Terms Equity NPV | B6: =SUMIF(Returns!$A$2:$A$41,"CURRENT_TERMS",Returns!$N$2:$N$41) -> -1.3378599e+11
A7: Negotiated Terms Equity NPV | B7: =SUMIF(Returns!$A$2:$A$41,"NEGOTIATED_TERMS",Returns!$N$2:$N$41) -> 1.583573e+10
A8: Formula gate | B8: =IF(COUNTIF(Returns!$Q$2:$Q$41,"CHECK")=0,"PASS","CHECK") -> CHECK
A9: Remote-only data boundary | B9: TRUE
A10: Model decision | B10: =IF(B6>0,"CURRENT TERMS DEPLOYMENT",IF(B7>0,"NEGOTIATED CANDIDATES","NO_DEPLOYMENT")) -> NEGOTIATED CANDIDATES
A12: Case | B12: Equity NPV
A13: CURRENT_TERMS | B13: =B6 -> 0
A14: NEGOTIATED_TERMS | B14: =B7 -> 0
